coze_coding_utils/__init__.py
coze_coding_utils/error/__init__.py
coze_coding_utils/error/classifier.py
coze_coding_utils/error/codes.py
coze_coding_utils/error/exceptions.py
coze_coding_utils/error/patterns.py
coze_coding_utils/error/test_classifier.py
coze_coding_utils/file/__init__.py
coze_coding_utils/file/file.py
coze_coding_utils/helper/__init__.py
coze_coding_utils/helper/agent_helper.py
coze_coding_utils/helper/graph_helper.py
coze_coding_utils/log/__init__.py
coze_coding_utils/log/common.py
coze_coding_utils/log/config.py
coze_coding_utils/log/err_trace.py
coze_coding_utils/log/loop_trace.py
coze_coding_utils/log/node_log.py
coze_coding_utils/log/parser.py
coze_coding_utils/log/write_log.py
coze_coding_utils/messages/__init__.py
coze_coding_utils/messages/client.py
coze_coding_utils/messages/server.py
coze_coding_utils/openai/__init__.py
coze_coding_utils/openai/handler.py
coze_coding_utils/openai/converter/__init__.py
coze_coding_utils/openai/converter/request_converter.py
coze_coding_utils/openai/converter/response_converter.py
coze_coding_utils/openai/types/__init__.py
coze_coding_utils/openai/types/request.py
coze_coding_utils/openai/types/response.py
coze_coding_utils/runtime_ctx/__init__.py
coze_coding_utils/runtime_ctx/context.py
coze_coding_utils-0.2.2.dist-info/METADATA
coze_coding_utils-0.2.2.dist-info/WHEEL
coze_coding_utils-0.2.2.dist-info/licenses/LICENSE
coze_coding_utils-0.2.2.dist-info/RECORD
