Metadata-Version: 2.4
Name: coze-coding-utils
Version: 0.2.2
Summary: Utilities for Coze coding client runtime context and helpers.
Project-URL: Homepage, https://code.byted.org/stone/coze-coding-client
Author: Bytedance Stone Team
License: MIT
License-File: LICENSE
Keywords: context,coze,utils
Classifier: License :: OSI Approved :: MIT License
Classifier: Operating System :: OS Independent
Classifier: Programming Language :: Python :: 3
Classifier: Programming Language :: Python :: 3.10
Requires-Python: >=3.10
